README.md
setup.py
rsatool/RSA_tool.py
rsatool/__init__.py
rsatool/encryption.py
rsatool/main.py
rsatool/prime_numbers.py
rsatool.egg-info/PKG-INFO
rsatool.egg-info/SOURCES.txt
rsatool.egg-info/dependency_links.txt
rsatool.egg-info/top_level.txt