Metadata-Version: 2.1
Name: rsatool
Version: 0.1.3
Summary: Module for fast calculating large primes, and RSA encryption and decryption of data of any size
Home-page: https://github.com/mrNikGrig/RSA_tool.git
Author: Nikita Grigorev
Author-email: nekitbilding@inbox.ru
